explainitall/__init__.py
explainitall/clusters.py
explainitall/nlp.py
explainitall/stat_helpers.py
explainitall/QA/extractive_qa_sbert/QABotsBase.py
explainitall/QA/extractive_qa_sbert/SVDBert.py
explainitall/QA/interp_qa/KNNWithGenerative.py
explainitall/embedder_interp/embd_interpret.py
explainitall/fast_tuning/Embedder.py
explainitall/fast_tuning/ExpertBase.py
explainitall/fast_tuning/SimpleModelCreator.py
explainitall/fast_tuning/generators/GeneratorWithExpert.py
explainitall/fast_tuning/generators/MCExpert.py
explainitall/fast_tuning/generators/MCModel.py
explainitall/fast_tuning/generators/SimpleGenerator.py
explainitall/fast_tuning/trainers/DenceKerasTrainer.py
explainitall/fast_tuning/trainers/HMMTrainer.py
explainitall/fast_tuning/trainers/ProjectionTrainer.py
explainitall/gpt_like_interp/__init__.py
explainitall/gpt_like_interp/downloader.py
explainitall/gpt_like_interp/inseq_helpers.py
explainitall/gpt_like_interp/interp.py
explainitall/gpt_like_interp/viz.py
explainitall/gui/df_to_heatmap_plot.py
explainitall/gui/interface.py
explainitall/metrics/CheckingForHallucinations.py
explainitall/metrics/RougeAndPPL/Metrics.py
explainitall/metrics/RougeAndPPL/Metrics_calculator.py
explainitall/metrics/RougeAndPPL/create_database.py
explainitall/metrics/RougeAndPPL/helpers.py
explainitall/metrics/RougeAndPPL/metric_calculation_interface.py
explainitall/metrics/RougeAndPPL/rouge_L.py
explainitall/metrics/RougeAndPPL/rouge_N.py
explainitall-1.0.2.dist-info/LICENSE
explainitall-1.0.2.dist-info/METADATA
explainitall-1.0.2.dist-info/WHEEL
explainitall-1.0.2.dist-info/top_level.txt
explainitall-1.0.2.dist-info/RECORD
