Metadata-Version: 2.1
Name: explainitall
Version: 1.0.2
License-File: LICENSE
Requires-Dist: gensim ==4.3.2
Requires-Dist: gradio ==4.4.1
Requires-Dist: gradio-client ==0.7.0
Requires-Dist: inseq ==0.5.0
Requires-Dist: matplotlib ==3.8.4
Requires-Dist: nltk ==3.8.1
Requires-Dist: pandas ==2.2.1
Requires-Dist: pymorphy2 ==0.9.1
Requires-Dist: scikit-learn ==1.4.1.post1
Requires-Dist: seaborn ==0.13.2
Requires-Dist: sentence-transformers ==2.6.1
Requires-Dist: SQLAlchemy ==2.0.29
Requires-Dist: statsmodels ==0.14.1
Requires-Dist: torch >=2.0
Requires-Dist: transformers >=4.39
Requires-Dist: uvicorn ==0.29
Requires-Dist: scipy ==1.12.0
Requires-Dist: numpy ==1.26.4
